readosso/__init__.py
readosso-0.1.3.dist-info/METADATA
readosso-0.1.3.dist-info/WHEEL
readosso-0.1.3.dist-info/top_level.txt
readosso-0.1.3.dist-info/RECORD
