Metadata-Version: 2.4
Name: readosso
Version: 0.1.3
Summary: URL
Author: M5TL
Author-email: 3asdad@gmail.com
Requires-Python: >=3.6
Requires-Dist: requests
Dynamic: author
Dynamic: author-email
Dynamic: description
Dynamic: description-content-type
Dynamic: requires-dist
Dynamic: requires-python
Dynamic: summary
